Workbook

Sheet All
A1: Contract Billing Calculator & Cost Reconciliation
A3: Purpose: calculate the expected charge for each billing line from contract terms, then reconcile against the amount actually invoiced.
A4: Data: SAMPLE / dummy contract rates and invoices created for this self-directed project.
A6: Sheets:
A7: Assumptions- GST rate and match tolerance (blue = editable inputs).
A8: Rate_Card- contract rate, volume-discount threshold/percent, and an old rate (to detect stale-rate billing).
A9: Billing_Reconciliation- Qty and Invoice_Amount are inputs (blue); everything else is formula.
A10: Summary- status counts, variance by service and by client.
A12: Calculation: Base = Qty x Rate | Discount = Base x Disc% if Qty > Threshold | Taxable = Base - Discount | GST = Taxable x GST rate | Expected = Taxable + GST.
A13: Status: Match if |Variance| <= tolerance, else Overbilled / Underbilled. Suspected_Cause tests common error patterns automatically.
A14: To add a bill: add a row at the bottom of Billing_Reconciliation, copy the formulas down from the row above, enter Qty and Invoice_Amount.
A15: Currency: INR.

Sheet Assumptions
A1: Assumptions
A3: GST rate | B3: 0.18 | C3: Assumed flat 18% GST on services
A4: Match tolerance (Rs) | B4: 1 | C4: Differences up to this amount are treated as rounding

Sheet Rate_Card
A1: Service | B1: Unit | C1: Contract_Rate | D1: Discount_Threshold_Qty | E1: Discount_Pct | F1: Old_Rate (pre-revision)
A2: IT Support (per hour) | B2: Hour | C2: 1200 | D2: 100 | E2: 0.05 | F2: 1000
A3: Cloud Storage (per TB) | B3: TB | C3: 4500 | D3: 10 | E3: 0.08 | F3: 4000
A4: Data Entry (per 1000 records) | B4: 1000 recs | C4: 650 | D4: 50 | E4: 0.05 | F4: 600
A5: Report Generation (per report) | B5: Report | C5: 900 | D5: 20 | E5: 0.1 | F5: 850
A6: Server Maintenance (per month) | B6: Month | C6: 15000 | D6: 3 | E6: 0.05 | F6: 14000

Sheet Billing_Reconciliation
A1: Bill_ID | B1: Period | C1: Client | D1: Service | E1: Qty | F1: Contract_Rate | G1: Base_Amount | H1: Discount | I1: Taxable_Amount | J1: GST | K1: Expected_Total | L1: Invoice_Amount | M1: Variance | N1: Variance_% | O1: Status | P1: Expected_at_Old_Rate | Q1: Suspected_Cause | R1: Remarks
A2: BILL-001 | B2: Jul-2026 | C2: Orion Retail | D2: Report Generation (per report) | E2: 25 | F2: =INDEX(Rate_Card!$C$2:$C$6,MATCH(D2,Rate_Card!$A$2:$A$6,0)) -> 900 | G2: =E2*F2 -> 22500 | H2: =IF(E2>INDEX(Rate_Card!$D$2:$D$6,MATCH(D2,Rate_Card!$A$2:$A$6,0)),G2*INDEX(Rate_Card!$E$2:$E$6,MATCH(D2,Rate_Card!$A$2:$A$6,0)),0) -> 2250 | I2: =G2-H2 -> 20250 | J2: =I2*Assumptions!$B$3 -> 3645 | K2: =ROUND(I2+J2,2) -> 23895 | L2: 26550 | M2: =ROUND(L2-K2,2) -> 2655 | N2: =IF(K2=0,0,M2/K2) -> 0.11111111 | O2: =IF(ABS(M2)<=Assumptions!$B$4,"Match",IF(M2>0,"Overbilled","Underbilled")) -> Overbilled | P2: =ROUND((E2*INDEX(Rate_Card!$F$2:$F$6,MATCH(D2,Rate_Card!$A$2:$A$6,0))-IF(E2>INDEX(Rate_Card!$D$2:$D$6,MATCH(D2,Rate_Card!$A$2:$A$6,0)),E2*INDEX(Rate_Card!$F$2:$F$6,MATCH(D2,Rate_Card!$A$2:$A$6,0))*INDEX(Rate_Card!$E$2:$E$6,MATCH(D2,Rate_Card!$A$2:$A$6,0)),0))*(1+Assumptions!$B$3),2) -> 22567.5 | Q2: =IF(O2="Match","",IF(ABS(L2-I2)<=Assumptions!$B$4,"GST not applied",IF(ABS(L2-G2*(1+Assumptions!$B$3))<=Assumptions!$B$4,"Volume discount not applied",IF(ABS(L2-P2)<=Assumptions!$B$4,"Old rate used","Review: qty / rate / other")))) -> Volume discount not applied
A3: BILL-002 | B3: Jul-2026 | C3: Orion Retail | D3: Server Maintenance (per month) | E3: 2 | F3: =INDEX(Rate_Card!$C$2:$C$6,MATCH(D3,Rate_Card!$A$2:$A$6,0)) -> 15000 | G3: =E3*F3 -> 30000 | H3: =IF(E3>INDEX(Rate_Card!$D$2:$D$6,MATCH(D3,Rate_Card!$A$2:$A$6,0)),G3*INDEX(Rate_Card!$E$2:$E$6,MATCH(D3,Rate_Card!$A$2:$A$6,0)),0) -> 0 | I3: =G3-H3 -> 30000 | J3: =I3*Assumptions!$B$3 -> 5400 | K3: =ROUND(I3+J3,2) -> 35400 | L3: 33040 | M3: =ROUND(L3-K3,2) -> -2360 | N3: =IF(K3=0,0,M3/K3) -> -0.066666667 | O3: =IF(ABS(M3)<=Assumptions!$B$4,"Match",IF(M3>0,"Overbilled","Underbilled")) -> Underbilled | P3: =ROUND((E3*INDEX(Rate_Card!$F$2:$F$6,MATCH(D3,Rate_Card!$A$2:$A$6,0))-IF(E3>INDEX(Rate_Card!$D$2:$D$6,MATCH(D3,Rate_Card!$A$2:$A$6,0)),E3*INDEX(Rate_Card!$F$2:$F$6,MATCH(D3,Rate_Card!$A$2:$A$6,0))*INDEX(Rate_Card!$E$2:$E$6,MATCH(D3,Rate_Card!$A$2:$A$6,0)),0))*(1+Assumptions!$B$3),2) -> 33040 | Q3: =IF(O3="Match","",IF(ABS(L3-I3)<=Assumptions!$B$4,"GST not applied",IF(ABS(L3-G3*(1+Assumptions!$B$3))<=Assumptions!$B$4,"Volume discount not applied",IF(ABS(L3-P3)<=Assumptions!$B$4,"Old rate used","Review: qty / rate / other")))) -> Old rate used
A4: BILL-003 | B4: Jul-2026 | C4: BlueLeaf Pharma | D4: Cloud Storage (per TB) | E4: 5 | F4: =INDEX(Rate_Card!$C$2:$C$6,MATCH(D4,Rate_Card!$A$2:$A$6,0)) -> 4500 | G4: =E4*F4 -> 22500 | H4: =IF(E4>INDEX(Rate_Card!$D$2:$D$6,MATCH(D4,Rate_Card!$A$2:$A$6,0)),G4*INDEX(Rate_Card!$E$2:$E$6,MATCH(D4,Rate_Card!$A$2:$A$6,0)),0) -> 0 | I4: =G4-H4 -> 22500 | J4: =I4*Assumptions!$B$3 -> 4050 | K4: =ROUND(I4+J4,2) -> 26550 | L4: 26550 | M4: =ROUND(L4-K4,2) -> 0 | N4: =IF(K4=0,0,M4/K4) -> 0 | O4: =IF(ABS(M4)<=Assumptions!$B$4,"Match",IF(M4>0,"Overbilled","Underbilled")) -> Match | P4: =ROUND((E4*INDEX(Rate_Card!$F$2:$F$6,MATCH(D4,Rate_Card!$A$2:$A$6,0))-IF(E4>INDEX(Rate_Card!$D$2:$D$6,MATCH(D4,Rate_Card!$A$2:$A$6,0)),E4*INDEX(Rate_Card!$F$2:$F$6,MATCH(D4,Rate_Card!$A$2:$A$6,0))*INDEX(Rate_Card!$E$2:$E$6,MATCH(D4,Rate_Card!$A$2:$A$6,0)),0))*(1+Assumptions!$B$3),2) -> 23600 | Q4: =IF(O4="Match","",IF(ABS(L4-I4)<=Assumptions!$B$4,"GST not applied",IF(ABS(L4-G4*(1+Assumptions!$B$3))<=Assumptions!$B$4,"Volume discount not applied",IF(ABS(L4-P4)<=Assumptions!$B$4,"Old rate used","Review: qty / rate / other"))))
A5: BILL-004 | B5: Jul-2026 | C5: BlueLeaf Pharma | D5: Report Generation (per report) | E5: 2 | F5: =INDEX(Rate_Card!$C$2:$C$6,MATCH(D5,Rate_Card!$A$2:$A$6,0)) -> 900 | G5: =E5*F5 -> 1800 | H5: =IF(E5>INDEX(Rate_Card!$D$2:$D$6,MATCH(D5,Rate_Card!$A$2:$A$6,0)),G5*INDEX(Rate_Card!$E$2:$E$6,MATCH(D5,Rate_Card!$A$2:$A$6,0)),0) -> 0 | I5: =G5-H5 -> 1800 | J5: =I5*Assumptions!$B$3 -> 324 | K5: =ROUND(I5+J5,2) -> 2124 | L5: 2124 | M5: =ROUND(L5-K5,2) -> 0 | N5: =IF(K5=0,0,M5/K5) -> 0 | O5: =IF(ABS(M5)<=Assumptions!$B$4,"Match",IF(M5>0,"Overbilled","Underbilled")) -> Match | P5: =ROUND((E5*INDEX(Rate_Card!$F$2:$F$6,MATCH(D5,Rate_Card!$A$2:$A$6,0))-IF(E5>INDEX(Rate_Card!$D$2:$D$6,MATCH(D5,Rate_Card!$A$2:$A$6,0)),E5*INDEX(Rate_Card!$F$2:$F$6,MATCH(D5,Rate_Card!$A$2:$A$6,0))*INDEX(Rate_Card!$E$2:$E$6,MATCH(D5,Rate_Card!$A$2:$A$6,0)),0))*(1+Assumptions!$B$3),2) -> 2006 | Q5: =IF(O5="Match","",IF(ABS(L5-I5)<=Assumptions!$B$4,"GST not applied",IF(ABS(L5-G5*(1+Assumptions!$B$3))<=Assumptions!$B$4,"Volume discount not applied",IF(ABS(L5-P5)<=Assumptions!$B$4,"Old rate used","Review: qty / rate / other"))))
A6: BILL-005 | B6: Jul-2026 | C6: Kiran Logistics | D6: Report Generation (per report) | E6: 5 | F6: =INDEX(Rate_Card!$C$2:$C$6,MATCH(D6,Rate_Card!$A$2:$A$6,0)) -> 900 | G6: =E6*F6 -> 4500 | H6: =IF(E6>INDEX(Rate_Card!$D$2:$D$6,MATCH(D6,Rate_Card!$A$2:$A$6,0)),G6*INDEX(Rate_Card!$E$2:$E$6,MATCH(D6,Rate_Card!$A$2:$A$6,0)),0) -> 0 | I6: =G6-H6 -> 4500 | J6: =I6*Assumptions!$B$3 -> 810 | K6: =ROUND(I6+J6,2) -> 5310 | L6: 4500 | M6: =ROUND(L6-K6,2) -> -810 | N6: =IF(K6=0,0,M6/K6) -> -0.15254237 | O6: =IF(ABS(M6)<=Assumptions!$B$4,"Match",IF(M6>0,"Overbilled","Underbilled")) -> Underbilled | P6: =ROUND((E6*INDEX(Rate_Card!$F$2:$F$6,MATCH(D6,Rate_Card!$A$2:$A$6,0))-IF(E6>INDEX(Rate_Card!$D$2:$D$6,MATCH(D6,Rate_Card!$A$2:$A$6,0)),E6*INDEX(Rate_Card!$F$2:$F$6,MATCH(D6,Rate_Card!$A$2:$A$6,0))*INDEX(Rate_Card!$E$2:$E$6,MATCH(D6,Rate_Card!$A$2:$A$6,0)),0))*(1+Assumptions!$B$3),2) -> 5015 | Q6: =IF(O6="Match","",IF(ABS(L6-I6)<=Assumptions!$B$4,"GST not applied",IF(ABS(L6-G6*(1+Assumptions!$B$3))<=Assumptions!$B$4,"Volume discount not applied",IF(ABS(L6-P6)<=Assumptions!$B$4,"Old rate used","Review: qty / rate / other")))) -> GST not applied
A7: BILL-006 | B7: Jul-2026 | C7: Kiran Logistics | D7: Data Entry (per 1000 records) | E7: 8 | F7: =INDEX(Rate_Card!$C$2:$C$6,MATCH(D7,Rate_Card!$A$2:$A$6,0)) -> 650 | G7: =E7*F7 -> 5200 | H7: =IF(E7>INDEX(Rate_Card!$D$2:$D$6,MATCH(D7,Rate_Card!$A$2:$A$6,0)),G7*INDEX(Rate_Card!$E$2:$E$6,MATCH(D7,Rate_Card!$A$2:$A$6,0)),0) -> 0 | I7: =G7-H7 -> 5200 | J7: =I7*Assumptions!$B$3 -> 936 | K7: =ROUND(I7+J7,2) -> 6136 | L7: 6136 | M7: =ROUND(L7-K7,2) -> 0 | N7: =IF(K7=0,0,M7/K7) -> 0 | O7: =IF(ABS(M7)<=Assumptions!$B$4,"Match",IF(M7>0,"Overbilled","Underbilled")) -> Match | P7: =ROUND((E7*INDEX(Rate_Card!$F$2:$F$6,MATCH(D7,Rate_Card!$A$2:$A$6,0))-IF(E7>INDEX(Rate_Card!$D$2:$D$6,MATCH(D7,Rate_Card!$A$2:$A$6,0)),E7*INDEX(Rate_Card!$F$2:$F$6,MATCH(D7,Rate_Card!$A$2:$A$6,0))*INDEX(Rate_Card!$E$2:$E$6,MATCH(D7,Rate_Card!$A$2:$A$6,0)),0))*(1+Assumptions!$B$3),2) -> 5664 | Q7: =IF(O7="Match","",IF(ABS(L7-I7)<=Assumptions!$B$4,"GST not applied",IF(ABS(L7-G7*(1+Assumptions!$B$3))<=Assumptions!$B$4,"Volume discount not applied",IF(ABS(L7-P7)<=Assumptions!$B$4,"Old rate used","Review: qty / rate / other"))))
A8: BILL-007 | B8: Aug-2026 | C8: Orion Retail | D8: Server Maintenance (per month) | E8: 4 | F8: =INDEX(Rate_Card!$C$2:$C$6,MATCH(D8,Rate_Card!$A$2:$A$6,0)) -> 15000 | G8: =E8*F8 -> 60000 | H8: =IF(E8>INDEX(Rate_Card!$D$2:$D$6,MATCH(D8,Rate_Card!$A$2:$A$6,0)),G8*INDEX(Rate_Card!$E$2:$E$6,MATCH(D8,Rate_Card!$A$2:$A$6,0)),0) -> 3000 | I8: =G8-H8 -> 57000 | J8: =I8*Assumptions!$B$3 -> 10260 | K8: =ROUND(I8+J8,2) -> 67260 | L8: 67260.4 | M8: =ROUND(L8-K8,2) -> 0.4 | N8: =IF(K8=0,0,M8/K8) -> 5.9470711e-06 | O8: =IF(ABS(M8)<=Assumptions!$B$4,"Match",IF(M8>0,"Overbilled","Underbilled")) -> Match | P8: =ROUND((E8*INDEX(Rate_Card!$F$2:$F$6,MATCH(D8,Rate_Card!$A$2:$A$6,0))-IF(E8>INDEX(Rate_Card!$D$2:$D$6,MATCH(D8,Rate_Card!$A$2:$A$6,0)),E8*INDEX(Rate_Card!$F$2:$F$6,MATCH(D8,Rate_Card!$A$2:$A$6,0))*INDEX(Rate_Card!$E$2:$E$6,MATCH(D8,Rate_Card!$A$2:$A$6,0)),0))*(1+Assumptions!$B$3),2) -> 62776 | Q8: =IF(O8="Match","",IF(ABS(L8-I8)<=Assumptions!$B$4,"GST not applied",IF(ABS(L8-G8*(1+Assumptions!$B$3))<=Assumptions!$B$4,"Volume discount not applied",IF(ABS(L8-P8)<=Assumptions!$B$4,"Old rate used","Review: qty / rate / other"))))
A9: BILL-008 | B9: Aug-2026 | C9: Orion Retail | D9: IT Support (per hour) | E9: 60 | F9: =INDEX(Rate_Card!$C$2:$C$6,MATCH(D9,Rate_Card!$A$2:$A$6,0)) -> 1200 | G9: =E9*F9 -> 72000 | H9: =IF(E9>INDEX(Rate_Card!$D$2:$D$6,MATCH(D9,Rate_Card!$A$2:$A$6,0)),G9*INDEX(Rate_Card!$E$2:$E$6,MATCH(D9,Rate_Card!$A$2:$A$6,0)),0) -> 0 | I9: =G9-H9 -> 72000 | J9: =I9*Assumptions!$B$3 -> 12960 | K9: =ROUND(I9+J9,2) -> 84960 | L9: 84960 | M9: =ROUND(L9-K9,2) -> 0 | N9: =IF(K9=0,0,M9/K9) -> 0 | O9: =IF(ABS(M9)<=Assumptions!$B$4,"Match",IF(M9>0,"Overbilled","Underbilled")) -> Match | P9: =ROUND((E9*INDEX(Rate_Card!$F$2:$F$6,MATCH(D9,Rate_Card!$A$2:$A$6,0))-IF(E9>INDEX(Rate_Card!$D$2:$D$6,MATCH(D9,Rate_Card!$A$2:$A$6,0)),E9*INDEX(Rate_Card!$F$2:$F$6,MATCH(D9,Rate_Card!$A$2:$A$6,0))*INDEX(Rate_Card!$E$2:$E$6,MATCH(D9,Rate_Card!$A$2:$A$6,0)),0))*(1+Assumptions!$B$3),2) -> 70800 | Q9: =IF(O9="Match","",IF(ABS(L9-I9)<=Assumptions!$B$4,"GST not applied",IF(ABS(L9-G9*(1+Assumptions!$B$3))<=Assumptions!$B$4,"Volume discount not applied",IF(ABS(L9-P9)<=Assumptions!$B$4,"Old rate used","Review: qty / rate / other"))))
A10: BILL-009 | B10: Aug-2026 | C10: BlueLeaf Pharma | D10: Server Maintenance (per month) | E10: 1 | F10: =INDEX(Rate_Card!$C$2:$C$6,MATCH(D10,Rate_Card!$A$2:$A$6,0)) -> 15000 | G10: =E10*F10 -> 15000 | H10: =IF(E10>INDEX(Rate_Card!$D$2:$D$6,MATCH(D10,Rate_Card!$A$2:$A$6,0)),G10*INDEX(Rate_Card!$E$2:$E$6,MATCH(D10,Rate_Card!$A$2:$A$6,0)),0) -> 0 | I10: =G10-H10 -> 15000 | J10: =I10*Assumptions!$B$3 -> 2700 | K10: =ROUND(I10+J10,2) -> 17700 | L10: 17700 | M10: =ROUND(L10-K10,2) -> 0 | N10: =IF(K10=0,0,M10/K10) -> 0 | O10: =IF(ABS(M10)<=Assumptions!$B$4,"Match",IF(M10>0,"Overbilled","Underbilled")) -> Match | P10: =ROUND((E10*INDEX(Rate_Card!$F$2:$F$6,MATCH(D10,Rate_Card!$A$2:$A$6,0))-IF(E10>INDEX(Rate_Card!$D$2:$D$6,MATCH(D10,Rate_Card!$A$2:$A$6,0)),E10*INDEX(Rate_Card!$F$2:$F$6,MATCH(D10,Rate_Card!$A$2:$A$6,0))*INDEX(Rate_Card!$E$2:$E$6,MATCH(D10,Rate_Card!$A$2:$A$6,0)),0))*(1+Assumptions!$B$3),2) -> 16520 | Q10: =IF(O10="Match","",IF(ABS(L10-I10)<=Assumptions!$B$4,"GST not applied",IF(ABS(L10-G10*(1+Assumptions!$B$3))<=Assumptions!$B$4,"Volume discount not applied",IF(ABS(L10-P10)<=Assumptions!$B$4,"Old rate used","Review: qty / rate / other"))))
A11: BILL-010 | B11: Aug-2026 | C11: BlueLeaf Pharma | D11: Cloud Storage (per TB) | E11: 2 | F11: =INDEX(Rate_Card!$C$2:$C$6,MATCH(D11,Rate_Card!$A$2:$A$6,0)) -> 4500 | G11: =E11*F11 -> 9000 | H11: =IF(E11>INDEX(Rate_Card!$D$2:$D$6,MATCH(D11,Rate_Card!$A$2:$A$6,0)),G11*INDEX(Rate_Card!$E$2:$E$6,MATCH(D11,Rate_Card!$A$2:$A$6,0)),0) -> 0 | I11: =G11-H11 -> 9000 | J11: =I11*Assumptions!$B$3 -> 1620 | K11: =ROUND(I11+J11,2) -> 10620 | L11: 26550 | M11: =ROUND(L11-K11,2) -> 15930 | N11: =IF(K11=0,0,M11/K11) -> 1.5 | O11: =IF(ABS(M11)<=Assumptions!$B$4,"Match",IF(M11>0,"Overbilled","Underbilled")) -> Overbilled | P11: =ROUND((E11*INDEX(Rate_Card!$F$2:$F$6,MATCH(D11,Rate_Card!$A$2:$A$6,0))-IF(E11>INDEX(Rate_Card!$D$2:$D$6,MATCH(D11,Rate_Card!$A$2:$A$6,0)),E11*INDEX(Rate_Card!$F$2:$F$6,MATCH(D11,Rate_Card!$A$2:$A$6,0))*INDEX(Rate_Card!$E$2:$E$6,MATCH(D11,Rate_Card!$A$2:$A$6,0)),0))*(1+Assumptions!$B$3),2) -> 9440 | Q11: =IF(O11="Match","",IF(ABS(L11-I11)<=Assumptions!$B$4,"GST not applied",IF(ABS(L11-G11*(1+Assumptions!$B$3))<=Assumptions!$B$4,"Volume discount not applied",IF(ABS(L11-P11)<=Assumptions!$B$4,"Old rate used","Review: qty / rate / other")))) -> Review: qty / rate / other
A12: BILL-011 | B12: Aug-2026 | C12: Kiran Logistics | D12: IT Support (per hour) | E12: 12 | F12: =INDEX(Rate_Card!$C$2:$C$6,MATCH(D12,Rate_Card!$A$2:$A$6,0)) -> 1200 | G12: =E12*F12 -> 14400 | H12: =IF(E12>INDEX(Rate_Card!$D$2:$D$6,MATCH(D12,Rate_Card!$A$2:$A$6,0)),G12*INDEX(Rate_Card!$E$2:$E$6,MATCH(D12,Rate_Card!$A$2:$A$6,0)),0) -> 0 | I12: =G12-H12 -> 14400 | J12: =I12*Assumptions!$B$3 -> 2592 | K12: =ROUND(I12+J12,2) -> 16992 | L12: 16992 | M12: =ROUND(L12-K12,2) -> 0 | N12: =IF(K12=0,0,M12/K12) -> 0 | O12: =IF(ABS(M12)<=Assumptions!$B$4,"Match",IF(M12>0,"Overbilled","Underbilled")) -> Match | P12: =ROUND((E12*INDEX(Rate_Card!$F$2:$F$6,MATCH(D12,Rate_Card!$A$2:$A$6,0))-IF(E12>INDEX(Rate_Card!$D$2:$D$6,MATCH(D12,Rate_Card!$A$2:$A$6,0)),E12*INDEX(Rate_Card!$F$2:$F$6,MATCH(D12,Rate_Card!$A$2:$A$6,0))*INDEX(Rate_Card!$E$2:$E$6,MATCH(D12,Rate_Card!$A$2:$A$6,0)),0))*(1+Assumptions!$B$3),2) -> 14160 | Q12: =IF(O12="Match","",IF(ABS(L12-I12)<=Assumptions!$B$4,"GST not applied",IF(ABS(L12-G12*(1+Assumptions!$B$3))<=Assumptions!$B$4,"Volume discount not applied",IF(ABS(L12-P12)<=Assumptions!$B$4,"Old rate used","Review: qty / rate / other"))))
A13: BILL-012 | B13: Aug-2026 | C13: Kiran Logistics | D13: Server Maintenance (per month) | E13: 2 | F13: =INDEX(Rate_Card!$C$2:$C$6,MATCH(D13,Rate_Card!$A$2:$A$6,0)) -> 15000 | G13: =E13*F13 -> 30000 | H13: =IF(E13>INDEX(Rate_Card!$D$2:$D$6,MATCH(D13,Rate_Card!$A$2:$A$6,0)),G13*INDEX(Rate_Card!$E$2:$E$6,MATCH(D13,Rate_Card!$A$2:$A$6,0)),0) -> 0 | I13: =G13-H13 -> 30000 | J13: =I13*Assumptions!$B$3 -> 5400 | K13: =ROUND(I13+J13,2) -> 35400 | L13: 35399.7 | M13: =ROUND(L13-K13,2) -> -0.3 | N13: =IF(K13=0,0,M13/K13) -> -8.4745763e-06 | O13: =IF(ABS(M13)<=Assumptions!$B$4,"Match",IF(M13>0,"Overbilled","Underbilled")) -> Match | P13: =ROUND((E13*INDEX(Rate_Card!$F$2:$F$6,MATCH(D13,Rate_Card!$A$2:$A$6,0))-IF(E13>INDEX(Rate_Card!$D$2:$D$6,MATCH(D13,Rate_Card!$A$2:$A$6,0)),E13*INDEX(Rate_Card!$F$2:$F$6,MATCH(D13,Rate_Card!$A$2:$A$6,0))*INDEX(Rate_Card!$E$2:$E$6,MATCH(D13,Rate_Card!$A$2:$A$6,0)),0))*(1+Assumptions!$B$3),2) -> 33040 | Q13: =IF(O13="Match","",IF(ABS(L13-I13)<=Assumptions!$B$4,"GST not applied",IF(ABS(L13-G13*(1+Assumptions!$B$3))<=Assumptions!$B$4,"Volume discount not applied",IF(ABS(L13-P13)<=Assumptions!$B$4,"Old rate used","Review: qty / rate / other"))))
... A19: BILL-018 | B19: Sep-2026 | C19: Kiran Logistics | D19: IT Support (per hour) | E19: 60 | F19: =INDEX(Rate_Card!$C$2:$C$6,MATCH(D19,Rate_Card!$A$2:$A$6,0)) -> 1200 | G19: =E19*F19 -> 72000 | H19: =IF(E19>INDEX(Rate_Card!$D$2:$D$6,MATCH(D19,Rate_Card!$A$2:$A$6,0)),G19*INDEX(Rate_Card!$E$2:$E$6,MATCH(D19,Rate_Card!$A$2:$A$6,0)),0) -> 0 | I19: =G19-H19 -> 72000 | J19: =I19*Assumptions!$B$3 -> 12960 | K19: =ROUND(I19+J19,2) -> 84960 | L19: 84960 | M19: =ROUND(L19-K19,2) -> 0 | N19: =IF(K19=0,0,M19/K19) -> 0 | O19: =IF(ABS(M19)<=Assumptions!$B$4,"Match",IF(M19>0,"Overbilled","Underbilled")) -> Match | P19: =ROUND((E19*INDEX(Rate_Card!$F$2:$F$6,MATCH(D19,Rate_Card!$A$2:$A$6,0))-IF(E19>INDEX(Rate_Card!$D$2:$D$6,MATCH(D19,Rate_Card!$A$2:$A$6,0)),E19*INDEX(Rate_Card!$F$2:$F$6,MATCH(D19,Rate_Card!$A$2:$A$6,0))*INDEX(Rate_Card!$E$2:$E$6,MATCH(D19,Rate_Card!$A$2:$A$6,0)),0))*(1+Assumptions!$B$3),2) -> 70800 | Q19: =IF(O19="Match","",IF(ABS(L19-I19)<=Assumptions!$B$4,"GST not applied",IF(ABS(L19-G19*(1+Assumptions!$B$3))<=Assumptions!$B$4,"Volume discount not applied",IF(ABS(L19-P19)<=Assumptions!$B$4,"Old rate used","Review: qty / rate / other"))))

Sheet Summary
A1: Reconciliation Summary
A2: Total bill lines | B2: =COUNTA(Billing_Reconciliation!A2:A19) -> 18
A3: Matched | B3: =COUNTIF(Billing_Reconciliation!O2:O19,"Match") -> 12
A4: Overbilled | B4: =COUNTIF(Billing_Reconciliation!O2:O19,"Overbilled") -> 3
A5: Underbilled | B5: =COUNTIF(Billing_Reconciliation!O2:O19,"Underbilled") -> 3
A6: Exception rate | B6: =IF(B2=0,0,(B4+B5)/B2) -> 0.33333333
A8: Total expected | B8: =SUM(Billing_Reconciliation!K2:K19) -> 607263.4
A9: Total invoiced | B9: =SUM(Billing_Reconciliation!L2:L19) -> 616538.5
A10: Net variance (invoiced - expected) | B10: =B9-B8 -> 9275.1
A11: Overbilled amount | B11: =SUMIF(Billing_Reconciliation!M2:M19,">"&Assumptions!B4) -> 21085
A12: Underbilled amount | B12: =SUMIF(Billing_Reconciliation!M2:M19,"<"&-Assumptions!B4) -> -11810
A14: Variance by service
A15: Service | B15: Expected | C15: Invoiced | D15: Variance
A16: =Rate_Card!A2 -> IT Support (per hour) | B16: =SUMIF(Billing_Reconciliation!D$2:D$19,A16,Billing_Reconciliation!K$2:K$19) -> 243552 | C16: =SUMIF(Billing_Reconciliation!D$2:D$19,A16,Billing_Reconciliation!L$2:L$19) -> 234912 | D16: =C16-B16 -> -8640
A17: =Rate_Card!A3 -> Cloud Storage (per TB) | B17: =SUMIF(Billing_Reconciliation!D$2:D$19,A17,Billing_Reconciliation!K$2:K$19) -> 95792.4 | C17: =SUMIF(Billing_Reconciliation!D$2:D$19,A17,Billing_Reconciliation!L$2:L$19) -> 114222.4 | D17: =C17-B17 -> 18430
A18: =Rate_Card!A4 -> Data Entry (per 1000 records) | B18: =SUMIF(Billing_Reconciliation!D$2:D$19,A18,Billing_Reconciliation!K$2:K$19) -> 6136 | C18: =SUMIF(Billing_Reconciliation!D$2:D$19,A18,Billing_Reconciliation!L$2:L$19) -> 6136 | D18: =C18-B18 -> 0
A19: =Rate_Card!A5 -> Report Generation (per report) | B19: =SUMIF(Billing_Reconciliation!D$2:D$19,A19,Billing_Reconciliation!K$2:K$19) -> 38763 | C19: =SUMIF(Billing_Reconciliation!D$2:D$19,A19,Billing_Reconciliation!L$2:L$19) -> 40608 | D19: =C19-B19 -> 1845
A20: =Rate_Card!A6 -> Server Maintenance (per month) | B20: =SUMIF(Billing_Reconciliation!D$2:D$19,A20,Billing_Reconciliation!K$2:K$19) -> 223020 | C20: =SUMIF(Billing_Reconciliation!D$2:D$19,A20,Billing_Reconciliation!L$2:L$19) -> 220660.1 | D20: =C20-B20 -> -2359.9
A22: Variance by client
A23: Client | B23: Expected | C23: Invoiced | D23: Variance
A24: Orion Retail | B24: =SUMIF(Billing_Reconciliation!C$2:C$19,A24,Billing_Reconciliation!K$2:K$19) -> 335415 | C24: =SUMIF(Billing_Reconciliation!C$2:C$19,A24,Billing_Reconciliation!L$2:L$19) -> 327070.4 | D24: =C24-B24 -> -8344.6
A25: BlueLeaf Pharma | B25: =SUMIF(Billing_Reconciliation!C$2:C$19,A25,Billing_Reconciliation!K$2:K$19) -> 120926.4 | C25: =SUMIF(Billing_Reconciliation!C$2:C$19,A25,Billing_Reconciliation!L$2:L$19) -> 139356.4 | D25: =C25-B25 -> 18430
A26: Kiran Logistics | B26: =SUMIF(Billing_Reconciliation!C$2:C$19,A26,Billing_Reconciliation!K$2:K$19) -> 150922 | C26: =SUMIF(Billing_Reconciliation!C$2:C$19,A26,Billing_Reconciliation!L$2:L$19) -> 150111.7 | D26: =C26-B26 -> -810.3
